latextree/__init__.py
latextree/bibliography.py
latextree/content.py
latextree/document.py
latextree/factory.py
latextree/ltree.py
latextree/macrosdef.py
latextree/node.py
latextree/parser.py
latextree/preprocessor.py
latextree/reader.py
latextree/settings.py
latextree/tabular.py
latextree/taxonomy.py
latextree/walker.py
latextree-0.2.dist-info/METADATA
latextree-0.2.dist-info/RECORD
latextree-0.2.dist-info/WHEEL
latextree-0.2.dist-info/entry_points.txt
latextree-0.2.dist-info/top_level.txt
