Metadata-Version: 2.1
Name: latextree
Version: 0.2
Summary: A document object model and related tools for Latex
Home-page: http://github.com/cardiffmaths/latextree
Author: D Evans
Author-email: evansd8@cf.ac.uk
License: MIT
Platform: UNKNOWN
Requires-Dist: jinja2
Requires-Dist: pylatexenc
Requires-Dist: bibtexparser
Requires-Dist: lxml
Requires-Dist: six
